pymount/__init__.py
pymount/mgr.py
pymount/static.py
pymount-0.0.11.dist-info/LICENSE
pymount-0.0.11.dist-info/METADATA
pymount-0.0.11.dist-info/WHEEL
pymount-0.0.11.dist-info/top_level.txt
pymount-0.0.11.dist-info/RECORD
