Metadata-Version: 2.1
Name: pymount
Version: 0.0.11
Summary: module to help you mount and unmount file systems
Home-page: https://veltzer.github.io/pymount
Download-URL: https://github.com/veltzer/pymount
Author: Mark Veltzer
Author-email: mark.veltzer@gmail.com
Maintainer: Mark Veltzer
Maintainer-email: mark.veltzer@gmail.com
License: MIT
Keywords: pymount,mount,umount,partition
Platform: python3
Classifier: Development Status :: 4 - Beta
Classifier: Environment :: Console
Classifier: Operating System :: OS Independent
Classifier: Programming Language :: Python
Classifier: Programming Language :: Python :: 3
Classifier: Programming Language :: Python :: 3 :: Only
Classifier: Programming Language :: Python :: 3.11
Classifier: Topic :: Utilities
Classifier: License :: OSI Approved :: MIT License
License-File: LICENSE
